{
  "main": {
    "id": "afbcfcb6970afa1d",
    "type": "split",
    "children": [
      {
        "id": "637d9cf70f7f57e2",
        "type": "tabs",
        "children": [
          {
            "id": "2d13d69586995025",
            "type": "leaf",
            "state": {
              "type": "markdown",
              "state": {
                "file": "README.md",
                "mode": "source",
                "source": false
              }
            }
          },
          {
            "id": "d43724fe773671d2",
            "type": "leaf",
            "state": {
              "type": "markdown",
              "state": {
                "file": "README.md",
                "mode": "source",
                "source": false
              }
            }
          },
          {
            "id": "58bb065d48842218",
            "type": "leaf",
            "state": {
              "type": "markdown",
              "state": {
                "file": "Banco de dados.md",
                "mode": "source",
                "source": false
              }
            }
          }
        ],
        "currentTab": 2
      }
    ],
    "direction": "vertical"
  },
  "left": {
    "id": "51bac323e7c05cea",
    "type": "split",
    "children": [
      {
        "id": "b95f5d524b5003f9",
        "type": "tabs",
        "children": [
          {
            "id": "4948b4cd0a46f53f",
            "type": "leaf",
            "state": {
              "type": "file-explorer",
              "state": {
                "sortOrder": "alphabetical"
              }
            }
          },
          {
            "id": "d7a4e5545d3a96fb",
            "type": "leaf",
            "state": {
              "type": "search",
              "state": {
                "query": "",
                "matchingCase": false,
                "explainSearch": false,
                "collapseAll": false,
                "extraContext": false,
                "sortOrder": "alphabetical"
              }
            }
          },
          {
            "id": "158a1e4455d3f47b",
            "type": "leaf",
            "state": {
              "type": "starred",
              "state": {}
            }
          }
        ]
      }
    ],
    "direction": "horizontal",
    "width": 300
  },
  "right": {
    "id": "dfd2b0484b8dabde",
    "type": "split",
    "children": [
      {
        "id": "3f84600d31e1f13a",
        "type": "tabs",
        "children": [
          {
            "id": "50be34867c8e916b",
            "type": "leaf",
            "state": {
              "type": "backlink",
              "state": {
                "file": "Banco de dados.md",
                "collapseAll": false,
                "extraContext": false,
                "sortOrder": "alphabetical",
                "showSearch": false,
                "searchQuery": "",
                "backlinkCollapsed": false,
                "unlinkedCollapsed": true
              }
            }
          },
          {
            "id": "5dc41135f8ce3457",
            "type": "leaf",
            "state": {
              "type": "outgoing-link",
              "state": {
                "file": "Banco de dados.md",
                "linksCollapsed": false,
                "unlinkedCollapsed": true
              }
            }
          },
          {
            "id": "7f1db3ff27a7d236",
            "type": "leaf",
            "state": {
              "type": "tag",
              "state": {
                "sortOrder": "frequency",
                "useHierarchy": true
              }
            }
          },
          {
            "id": "82f93a43688eb5ac",
            "type": "leaf",
            "state": {
              "type": "outline",
              "state": {
                "file": "Banco de dados.md"
              }
            }
          }
        ]
      }
    ],
    "direction": "horizontal",
    "width": 300
  },
  "left-ribbon": {
    "hiddenItems": {
      "switcher:Open quick switcher": false,
      "graph:Open graph view": false,
      "canvas:Create new canvas": false,
      "daily-notes:Open today's daily note": false,
      "templates:Insert template": false,
      "command-palette:Open command palette": false
    }
  },
  "active": "58bb065d48842218",
  "lastOpenFiles": [
    "README.md",
    "Banco de dados.md",
    "Assets/ModelagensMda.mdj",
    "Assets",
    "Assets/Pasted image 20230320143235.png",
    "Roda da Vida.md",
    "Features"
  ]
}